SpatialHumanHeart/__init__.py
SpatialHumanHeart/preprocessing/MakeAnndata.py
SpatialHumanHeart/preprocessing/__init__.py
SpatialHumanHeart/preprocessing/analysation.py
SpatialHumanHeart/preprocessing/remove_mt_ribo.py
SpatialHumanHeart-0.0.4.dist-info/METADATA
SpatialHumanHeart-0.0.4.dist-info/WHEEL
SpatialHumanHeart-0.0.4.dist-info/top_level.txt
SpatialHumanHeart-0.0.4.dist-info/RECORD
