Metadata-Version: 2.1
Name: SpatialHumanHeart
Version: 0.0.4
Summary: Python package for analysis of slide-seq data on heart tissue
Author: Mercedes Dalman
Author-email: meraljopedal@gmail.com
Keywords: python,spatial transcriptomics,slide-seq,heart tissue,human heart
Classifier: Development Status :: 3 - Alpha
Classifier: Intended Audience :: Education
Classifier: Programming Language :: Python :: 2
Classifier: Programming Language :: Python :: 3
Classifier: Operating System :: MacOS :: MacOS X
Classifier: Operating System :: Microsoft :: Windows
Requires-Dist: pandas
Requires-Dist: scanpy
Requires-Dist: seaborn
Requires-Dist: matplotlib
Requires-Dist: numpy
